creds/__init__.py
creds/constants.py
creds/constants.pyi
creds/plan.py
creds/plan.pyi
creds/ssh.py
creds/ssh.pyi
creds/users.py
creds/users.pyi
creds/utils.py
creds/utils.pyi
external/__init__.py
external/six/__init__.py
creds-1.0.16.dist-info/LICENSE
creds-1.0.16.dist-info/METADATA
creds-1.0.16.dist-info/WHEEL
creds-1.0.16.dist-info/top_level.txt
creds-1.0.16.dist-info/RECORD
